fastapi_cache/__init__.py
fastapi_cache/version.py
fastapi_cache/backends/__init__.py
fastapi_cache/backends/base.py
fastapi_cache/backends/memory.py
fastapi_cache/backends/redis.py
fastapi_cache-0.0.3.dist-info/LICENSE
fastapi_cache-0.0.3.dist-info/METADATA
fastapi_cache-0.0.3.dist-info/WHEEL
fastapi_cache-0.0.3.dist-info/top_level.txt
fastapi_cache-0.0.3.dist-info/RECORD
