Metadata-Version: 2.1
Name: fastapi-cache
Version: 0.0.3
Summary: FastAPI simple cache
Home-page: https://github.com/comeuplater/fastapi_cache
Author: Ivan Sushkov <comeuplater>
License: MIT License
Keywords: redis,aioredis,asyncio,fastapi,starlette,cache
Platform: UNKNOWN
Requires-Dist: aioredis (==1.3.1)
